shadowbot/__init__.py
shadowbot/service_init.py
shadowbot/utils/__init__.py
shadowbot/utils/_data_monitor.py
shadowbot/utils/_data_storage.py
shadowbot/utils/_function_doctor.py
shadowbot/utils/_function_share.py
shadowbot-0.1.0.dist-info/licenses/LICENSE
shadowbot-0.1.0.dist-info/METADATA
shadowbot-0.1.0.dist-info/WHEEL
shadowbot-0.1.0.dist-info/top_level.txt
shadowbot-0.1.0.dist-info/RECORD
