Metadata-Version: 2.4
Name: shadowbot
Version: 0.1.0
Summary: A Python package for scientific management of RPA processes.
Author-email: LKDD <lkddao@outlook.com>, LKDD <648429038@qq.com>
Classifier: Programming Language :: Python :: 3.13
Classifier: Programming Language :: Python :: 3.8
Classifier: License :: OSI Approved :: MIT License
Classifier: Operating System :: OS Independent
Classifier: Topic :: Software Development :: Libraries :: Python Modules
Requires-Python: >=3.8
License-File: LICENSE
Requires-Dist: requests>=2.32.3
Requires-Dist: pytz>=2024.2
Requires-Dist: tzlocal>=5.2
Dynamic: license-file
